README.md
setup.cfg
setup.py
coinpaprika/__init__.py
coinpaprika/client.py
coinpaprika/exceptions.py
coinpaprika.egg-info/PKG-INFO
coinpaprika.egg-info/SOURCES.txt
coinpaprika.egg-info/dependency_links.txt
coinpaprika.egg-info/requires.txt
coinpaprika.egg-info/top_level.txt