Metadata-Version: 1.1
Name: coinpaprika
Version: 0.1.0
Summary: Coinpaprika API Python client
Home-page: https://github.com/s0h3ck/coinpaprika-api-python-client/
Author: s0h3ck
Author-email: s0h3ck@gmail.com
License: MIT
Keywords: coinpaprika api cryptocurrency
Platform: UNKNOWN
Classifier: Programming Language :: Python :: 3
Classifier: License :: OSI Approved :: MIT License
Classifier: Operating System :: OS Independent
Classifier: Intended Audience :: Developers
Classifier: Topic :: Software Development :: Libraries :: Python Modules
